dinoskynet/__init__.py
dinoskynet/__main__.py
dinoskynet/version.py
dinoskynet/autonomous_agent/__init__.py
dinoskynet/autonomous_agent/autonomous_agent.py
dino_skynet-0.2.5.dist-info/LICENSE
dino_skynet-0.2.5.dist-info/METADATA
dino_skynet-0.2.5.dist-info/WHEEL
dino_skynet-0.2.5.dist-info/top_level.txt
dino_skynet-0.2.5.dist-info/RECORD
