Metadata-Version: 2.1
Name: dino-skynet
Version: 0.2.5
Summary: A simple implementation of an autonomous agent which exploits OpenCV to play the famous dino game
Home-page: https://github.com/RobertoBochet/dino-skynet
Author: Roberto Bochet
Author-email: robertobochet@gmail.com
License: gpl-3.0
Keywords: game,dino,pygame,opencv,computer vision,autonomous agent
Classifier: Development Status :: 4 - Beta
Classifier: Intended Audience :: Developers
Classifier: Intended Audience :: Education
Classifier: Intended Audience :: Science/Research
Classifier: Operating System :: OS Independent
Classifier: License :: OSI Approved :: GNU General Public License v3 (GPLv3)
Classifier: Programming Language :: Python :: 3
Requires-Python: >=3.6
License-File: LICENSE
Requires-Dist: dino-game ~=0.2
Requires-Dist: opencv-python ~=4.9.0
